{
  "Caxias": {
    "mes_referencia": "2026-03",
    "timestamp": "2026-03-12T14:39:31.801959",
    "indicadores": {
      "ortodontia": {
        "meta": "51.000,00",
        "ate_o_momento": "8.283,90",
        "falta": "-42.716,10",
        "progresso": "16,243%"
      },
      "clinico_geral": {
        "meta": "91.000,00",
        "ate_o_momento": "10.702,00",
        "falta": "-80.298,00",
        "progresso": "11,760%"
      },
      "meta_avaliacao": {
        "meta": "205",
        "ate_o_momento": "51",
        "falta": "-154",
        "progresso": "24,878%"
      },
      "meta_profilaxia": {
        "meta": "83",
        "ate_o_momento": "27",
        "falta": "-56",
        "progresso": "32,530%"
      },
      "meta_restauracao": {
        "meta": "79",
        "ate_o_momento": "8",
        "falta": "-71",
        "progresso": "10,127%"
      },
      "avaliacoes_google": {
        "meta": "",
        "ate_o_momento": "0",
        "falta": "",
        "progresso": ""
      }
    }
  },
  "Farroupilha": {
    "mes_referencia": "2026-03",
    "timestamp": "2026-03-12T14:40:26.318206",
    "indicadores": {
      "ortodontia": {
        "meta": "34.000,00",
        "ate_o_momento": "9.382,00",
        "falta": "-24.618,00",
        "progresso": "27,594%"
      },
      "clinico_geral": {
        "meta": "34.000,00",
        "ate_o_momento": "6.859,00",
        "falta": "-27.141,00",
        "progresso": "20,174%"
      },
      "meta_avaliacao": {
        "meta": "65",
        "ate_o_momento": "28",
        "falta": "-37",
        "progresso": "43,077%"
      },
      "meta_profilaxia": {
        "meta": "37",
        "ate_o_momento": "10",
        "falta": "-27",
        "progresso": "27,027%"
      },
      "meta_restauracao": {
        "meta": "18",
        "ate_o_momento": "7",
        "falta": "-11",
        "progresso": "38,889%"
      },
      "avaliacoes_google": {
        "meta": "",
        "ate_o_momento": "0",
        "falta": "",
        "progresso": ""
      }
    }
  },
  "Bento": {
    "mes_referencia": "2026-03",
    "timestamp": "2026-03-12T14:41:20.466119",
    "indicadores": {
      "ortodontia": {
        "meta": "26.000,00",
        "ate_o_momento": "8.479,00",
        "falta": "-17.521,00",
        "progresso": "32,612%"
      },
      "clinico_geral": {
        "meta": "25.000,00",
        "ate_o_momento": "8.228,99",
        "falta": "-16.771,01",
        "progresso": "32,916%"
      },
      "meta_avaliacao": {
        "meta": "99",
        "ate_o_momento": "25",
        "falta": "-74",
        "progresso": "25,253%"
      },
      "meta_profilaxia": {
        "meta": "42",
        "ate_o_momento": "17",
        "falta": "-25",
        "progresso": "40,476%"
      },
      "meta_restauracao": {
        "meta": "15",
        "ate_o_momento": "6",
        "falta": "-9",
        "progresso": "40,000%"
      },
      "avaliacoes_google": {
        "meta": "",
        "ate_o_momento": "0",
        "falta": "",
        "progresso": ""
      }
    }
  },
  "Encantado": {
    "mes_referencia": "2026-03",
    "timestamp": "2026-03-12T14:42:14.761871",
    "indicadores": {
      "ortodontia": {
        "meta": "39.000,00",
        "ate_o_momento": "10.685,00",
        "falta": "-28.315,00",
        "progresso": "27,397%"
      },
      "clinico_geral": {
        "meta": "31.000,00",
        "ate_o_momento": "8.426,00",
        "falta": "-22.574,00",
        "progresso": "27,181%"
      },
      "meta_avaliacao": {
        "meta": "109",
        "ate_o_momento": "21",
        "falta": "-88",
        "progresso": "19,266%"
      },
      "meta_profilaxia": {
        "meta": "19",
        "ate_o_momento": "4",
        "falta": "-15",
        "progresso": "21,053%"
      },
      "meta_restauracao": {
        "meta": "24",
        "ate_o_momento": "4",
        "falta": "-20",
        "progresso": "16,667%"
      },
      "avaliacoes_google": {
        "meta": "",
        "ate_o_momento": "0",
        "falta": "",
        "progresso": ""
      }
    }
  },
  "Soledade": {
    "mes_referencia": "2026-03",
    "timestamp": "2026-03-12T14:43:08.610086",
    "indicadores": {
      "ortodontia": {
        "meta": "58.000,00",
        "ate_o_momento": "15.353,99",
        "falta": "-42.646,01",
        "progresso": "26,472%"
      },
      "clinico_geral": {
        "meta": "40.000,00",
        "ate_o_momento": "6.591,00",
        "falta": "-33.409,00",
        "progresso": "16,478%"
      },
      "meta_avaliacao": {
        "meta": "320",
        "ate_o_momento": "100",
        "falta": "-220",
        "progresso": "31,250%"
      },
      "meta_profilaxia": {
        "meta": "88",
        "ate_o_momento": "22",
        "falta": "-66",
        "progresso": "25,000%"
      },
      "meta_restauracao": {
        "meta": "46",
        "ate_o_momento": "7",
        "falta": "-39",
        "progresso": "15,217%"
      },
      "avaliacoes_google": {
        "meta": "",
        "ate_o_momento": "0",
        "falta": "",
        "progresso": ""
      }
    }
  },
  "Garibaldi": {
    "mes_referencia": "2026-03",
    "timestamp": "2026-03-12T14:44:02.377205",
    "indicadores": {
      "ortodontia": {
        "meta": "37.500,00",
        "ate_o_momento": "17.790,00",
        "falta": "-19.710,00",
        "progresso": "47,440%"
      },
      "clinico_geral": {
        "meta": "28.000,00",
        "ate_o_momento": "5.761,00",
        "falta": "-22.239,00",
        "progresso": "20,575%"
      },
      "meta_avaliacao": {
        "meta": "76",
        "ate_o_momento": "28",
        "falta": "-48",
        "progresso": "36,842%"
      },
      "meta_profilaxia": {
        "meta": "40",
        "ate_o_momento": "13",
        "falta": "-27",
        "progresso": "32,500%"
      },
      "meta_restauracao": {
        "meta": "34",
        "ate_o_momento": "3",
        "falta": "-31",
        "progresso": "8,824%"
      },
      "avaliacoes_google": {
        "meta": "",
        "ate_o_momento": "0",
        "falta": "",
        "progresso": ""
      }
    }
  },
  "Veranópolis": {
    "mes_referencia": "2026-03",
    "timestamp": "2026-03-12T14:44:56.288746",
    "indicadores": {
      "ortodontia": {
        "meta": "29.000,00",
        "ate_o_momento": "6.611,69",
        "falta": "-22.388,31",
        "progresso": "22,799%"
      },
      "clinico_geral": {
        "meta": "17.700,00",
        "ate_o_momento": "7.423,00",
        "falta": "-10.277,00",
        "progresso": "41,938%"
      },
      "meta_avaliacao": {
        "meta": "52",
        "ate_o_momento": "20",
        "falta": "-32",
        "progresso": "38,462%"
      },
      "meta_profilaxia": {
        "meta": "15",
        "ate_o_momento": "8",
        "falta": "-7",
        "progresso": "53,333%"
      },
      "meta_restauracao": {
        "meta": "22",
        "ate_o_momento": "4",
        "falta": "-18",
        "progresso": "18,182%"
      },
      "avaliacoes_google": {
        "meta": "",
        "ate_o_momento": "0",
        "falta": "",
        "progresso": ""
      }
    }
  },
  "SS do Caí": {
    "mes_referencia": "2026-03",
    "timestamp": "2026-03-12T14:45:52.270216",
    "indicadores": {
      "ortodontia": {
        "meta": "25.000,00",
        "ate_o_momento": "8.137,00",
        "falta": "-16.863,00",
        "progresso": "32,548%"
      },
      "clinico_geral": {
        "meta": "16.000,00",
        "ate_o_momento": "4.944,00",
        "falta": "-11.056,00",
        "progresso": "30,900%"
      },
      "meta_avaliacao": {
        "meta": "68",
        "ate_o_momento": "18",
        "falta": "-50",
        "progresso": "26,471%"
      },
      "meta_profilaxia": {
        "meta": "24",
        "ate_o_momento": "4",
        "falta": "-20",
        "progresso": "16,667%"
      },
      "meta_restauracao": {
        "meta": "15",
        "ate_o_momento": "1",
        "falta": "-14",
        "progresso": "6,667%"
      },
      "avaliacoes_google": {
        "meta": "",
        "ate_o_momento": "0",
        "falta": "",
        "progresso": ""
      }
    }
  },
  "Flores": {
    "mes_referencia": "2026-03",
    "timestamp": "2026-03-12T14:46:47.217694",
    "indicadores": {
      "ortodontia": {
        "meta": "29.000,00",
        "ate_o_momento": "9.284,00",
        "falta": "-19.716,00",
        "progresso": "32,014%"
      },
      "clinico_geral": {
        "meta": "41.000,00",
        "ate_o_momento": "9.649,50",
        "falta": "-31.350,50",
        "progresso": "23,535%"
      },
      "meta_avaliacao": {
        "meta": "134",
        "ate_o_momento": "42",
        "falta": "-92",
        "progresso": "31,343%"
      },
      "meta_profilaxia": {
        "meta": "59",
        "ate_o_momento": "10",
        "falta": "-49",
        "progresso": "16,949%"
      },
      "meta_restauracao": {
        "meta": "61",
        "ate_o_momento": "8",
        "falta": "-53",
        "progresso": "13,115%"
      },
      "avaliacoes_google": {
        "meta": "",
        "ate_o_momento": "0",
        "falta": "",
        "progresso": ""
      }
    }
  }
}